ck_apstra_api/__init__.py
ck_apstra_api/apstra_blueprint.py
ck_apstra_api/apstra_session.py
ck_apstra_api/connectivity_template.py
ck_apstra_api/generic_system.py
ck_apstra_api/ip_endpoint.py
ck_apstra_api/pull_device_configuration.py
ck_apstra_api/util.py
ck_apstra_api/cli/__init__.py
ck_apstra_api/cli/blueprint.py
ck_apstra_api/cli/cli.py
ck_apstra_api/cli/configlet_validate.py
ck_apstra_api/cli/dci.py
ck_apstra_api/cli/ip_link.py
ck_apstra_api/cli/routing_zone.py
ck_apstra_api/cli/system.py
ck_apstra_api/cli/virtual_network.py
ck_apstra_api/cli/vlan_cts.py
ck_apstra_api-0.5.13.dist-info/licenses/LICENSE
ck_apstra_api-0.5.13.dist-info/METADATA
ck_apstra_api-0.5.13.dist-info/WHEEL
ck_apstra_api-0.5.13.dist-info/entry_points.txt
ck_apstra_api-0.5.13.dist-info/top_level.txt
ck_apstra_api-0.5.13.dist-info/RECORD
