Metadata-Version: 2.4
Name: ck-apstra-api
Version: 0.5.13
Summary: An implementation to use Apstra API
Author-email: Charlie Kim <ckim@juniper.net>
License-Expression: MIT
Requires-Python: >=3.11
License-File: LICENSE
Requires-Dist: click>=8.1.7
Requires-Dist: jinja2>=3.1.5
Requires-Dist: python-dotenv>=1.0.1
Requires-Dist: pyyaml>=6.0.2
Requires-Dist: requests>=2.32.3
Requires-Dist: result>=0.17.0
Dynamic: license-file
